{
  "lastUpdated": "2025-10-24T14:30:00Z",
  "note": "Today's matches have been carefully analyzed. Remember to bet responsibly!",

  "tips": [
    {
      "match": "Al-Fayha FC  🆚 Al-Hazm",
      "league": "Saudi Arabia Pro League",
      "tip": "Under 4.5 Goals",
      "odds": 1.16,
      "time": "14:50",
      "status": "pending",
      "confidence": 90,
      "createdAt": "2024-01-15T10:00:00Z"
    },
    {
      "match": "Ethiopian Coffee 🆚 Dire Dawa Kenewa",
      "league": "Ethiopia – Premier League",
      "tip": "Over 0.5 Goals",
      "odds": 1.17,
      "time": "13:00",
      "status": "pending",
      "confidence": 90,
      "createdAt": "2024-01-14T09:15:00Z"
    },
    {
      "match": "Bourj FC 🆚 Al Ahed FC",
      "league": "Lebanon – Premier League",
      "tip": "Away Over 0.5 Goals",
      "odds": 1.19,
      "time": "12:15",
      "status": "pending",
      "confidence": 80,
      "createdAt": "2024-01-13T11:30:00Z"
    }
  ]
}
