{
  "lastUpdated": "2025-10-24T14:30:00Z",
   "note": "Today's matches have been carefully analyzed. Remember to bet responsibly!",
  "tips": [
    {
      "match": "Gorna Oryahovitsa 🆚 PFC Spartak Pleven",
      "league": "Bulgaria - Vtora Liga",
      "tip": "Home or Draw",
      "odds": 1.15,
      "time": "12:30",
      "status": "won",
      "createdAt": "2024-01-15T10:00:00Z"
    },
    {
      "match": "Hacken Gothenburg 🆚 Piteaa IF DFF",
      "league": "Sweden - Damallsvenskan",
      "tip": "Home First Goal",
      "odds": 1.21,
      "time": "13:00",
      "status": "won",
      "createdAt": "2024-01-14T09:15:00Z"
    },
    {
      "match": "Malmo FF  🆚 Vittsjo GIK",
      "league": "Sweden - Damallsvenskan",
      "tip": "Home or Away",
      "odds": 1.25,
      "time": "17:00",
      "status": "won",
      "createdAt": "2024-01-15T11:30:00Z"
    }
  ]
}
